<annotation>
	<folder>labelimgdata</folder>
	<filename>picroadfault_raw_1197.jpg</filename>
	<path>C:\YOLO-v3\datasets\labelimgdata\picroadfault_raw_1197.jpg</path>
	<source>
		<database>Unknown</database>
	</source>
	<size>
		<width>980</width>
		<height>648</height>
		<depth>3</depth>
	</size>
	<segmented>0</segmented>
	<object>
		<name>pothole</name>
		<pose>Unspecified</pose>
		<truncated>0</truncated>
		<difficult>0</difficult>
		<bndbox>
			<xmin>321</xmin>
			<ymin>114</ymin>
			<xmax>469</xmax>
			<ymax>186</ymax>
		</bndbox>
	</object>
	<object>
		<name>pothole</name>
		<pose>Unspecified</pose>
		<truncated>0</truncated>
		<difficult>0</difficult>
		<bndbox>
			<xmin>241</xmin>
			<ymin>54</ymin>
			<xmax>346</xmax>
			<ymax>100</ymax>
		</bndbox>
	</object>
	<object>
		<name>pothole</name>
		<pose>Unspecified</pose>
		<truncated>0</truncated>
		<difficult>0</difficult>
		<bndbox>
			<xmin>545</xmin>
			<ymin>310</ymin>
			<xmax>713</xmax>
			<ymax>419</ymax>
		</bndbox>
	</object>
	<object>
		<name>pothole</name>
		<pose>Unspecified</pose>
		<truncated>1</truncated>
		<difficult>0</difficult>
		<bndbox>
			<xmin>533</xmin>
			<ymin>487</ymin>
			<xmax>823</xmax>
			<ymax>648</ymax>
		</bndbox>
	</object>
	<object>
		<name>pothole</name>
		<pose>Unspecified</pose>
		<truncated>0</truncated>
		<difficult>0</difficult>
		<bndbox>
			<xmin>846</xmin>
			<ymin>116</ymin>
			<xmax>966</xmax>
			<ymax>193</ymax>
		</bndbox>
	</object>
	<object>
		<name>pothole</name>
		<pose>Unspecified</pose>
		<truncated>0</truncated>
		<difficult>0</difficult>
		<bndbox>
			<xmin>719</xmin>
			<ymin>37</ymin>
			<xmax>793</xmax>
			<ymax>68</ymax>
		</bndbox>
	</object>
	<object>
		<name>pothole</name>
		<pose>Unspecified</pose>
		<truncated>1</truncated>
		<difficult>0</difficult>
		<bndbox>
			<xmin>909</xmin>
			<ymin>267</ymin>
			<xmax>980</xmax>
			<ymax>341</ymax>
		</bndbox>
	</object>
	<object>
		<name>pothole</name>
		<pose>Unspecified</pose>
		<truncated>0</truncated>
		<difficult>0</difficult>
		<bndbox>
			<xmin>355</xmin>
			<ymin>201</ymin>
			<xmax>440</xmax>
			<ymax>249</ymax>
		</bndbox>
	</object>
</annotation>
